llmtranslate/__init__.py
llmtranslate/benchmark/__init__.py
llmtranslate/benchmark/benchmark_core.py
llmtranslate/benchmark/data/__init__.py
llmtranslate/benchmark/data/short_text.py
llmtranslate/benchmark/data/short_text_data.py
llmtranslate/benchmark/format_benchmark_output.py
llmtranslate/benchmark/short_benchmark.py
llmtranslate/benchmark/to_del.py
llmtranslate/exceptions.py
llmtranslate/translator.py
llmtranslate/utils/__init__.py
llmtranslate/utils/available_languages.py
llmtranslate/utils/text_splitter.py
llmtranslate-0.7.13.dist-info/LICENSE
llmtranslate-0.7.13.dist-info/METADATA
llmtranslate-0.7.13.dist-info/WHEEL
llmtranslate-0.7.13.dist-info/RECORD
