Metadata-Version: 2.3
Name: llmtranslate
Version: 0.7.13
Summary: A Python library for language detection and translation using langchain ChatModels
Author: Adam Pawelek
Author-email: adam.pwk@outlook.com
Requires-Python: >=3.10,<4.0
Classifier: Programming Language :: Python :: 3
Classifier: Programming Language :: Python :: 3.10
Classifier: Programming Language :: Python :: 3.11
Classifier: Programming Language :: Python :: 3.12
Classifier: Programming Language :: Python :: 3.13
Requires-Dist: aiohttp (>=3.10.9,<4.0.0)
Requires-Dist: asyncio (>=3.4.3,<4.0.0)
Requires-Dist: langchain (>=0.3.14,<0.4.0)
Requires-Dist: langchain-core (>=0.3.32,<0.4.0)
Project-URL: documentation, https://llm-translate.com/
Project-URL: source, https://github.com/adam-pawelek/llmtranslate
